text_processing/__init__.py
text_processing/text_preprocessor.py
tweetprocessor_1-1.0.0.dist-info/LICENSE
tweetprocessor_1-1.0.0.dist-info/METADATA
tweetprocessor_1-1.0.0.dist-info/WHEEL
tweetprocessor_1-1.0.0.dist-info/top_level.txt
tweetprocessor_1-1.0.0.dist-info/RECORD
