Metadata-Version: 2.1
Name: tweetprocessor-1
Version: 1.0.0
Summary: This is my text processor that will process text using 10 NLP processing tehcniques for the ML SPECIALIZATION
Home-page: 
Author: Jhonatan Camasca
Requires-Python: ==3.12
License-File: LICENSE
Requires-Dist: pandas ==2.1.4
Requires-Dist: pytest ==6.2.4
Requires-Dist: nltk ==3.6.5
Requires-Dist: setuptools ==69.0.2
Requires-Dist: jupyter ==1.0.0
